bgoncotree/__init__.py
bgoncotree/cli.py
bgoncotree/exceptions.py
bgoncotree/main.py
bgoncotree/utils.py
bgoncotree-0.5.dist-info/LICENSE
bgoncotree-0.5.dist-info/METADATA
bgoncotree-0.5.dist-info/WHEEL
bgoncotree-0.5.dist-info/entry_points.txt
bgoncotree-0.5.dist-info/top_level.txt
bgoncotree-0.5.dist-info/RECORD
