Metadata-Version: 2.1
Name: bgoncotree
Version: 0.5
Summary: BBGLab interface for an OncoTree
Home-page: https://bitbucket.org/bgframework/bgoncotree
Author: Barcelona Biomedical Genomics Lab
Author-email: bbglab@irbbarcelona.org
License: Apache Software License 2.0
Platform: UNKNOWN
Requires-Dist: bgdata (>=2)
Requires-Dist: click
